odoo/addons/product_sequence/README.rst
odoo/addons/product_sequence/__init__.py
odoo/addons/product_sequence/__manifest__.py
odoo/addons/product_sequence/hooks.py
odoo/addons/product_sequence/data/product_sequence.xml
odoo/addons/product_sequence/i18n/ar.po
odoo/addons/product_sequence/i18n/bg.po
odoo/addons/product_sequence/i18n/bs.po
odoo/addons/product_sequence/i18n/ca.po
odoo/addons/product_sequence/i18n/cs.po
odoo/addons/product_sequence/i18n/da.po
odoo/addons/product_sequence/i18n/de.po
odoo/addons/product_sequence/i18n/el.po
odoo/addons/product_sequence/i18n/es.po
odoo/addons/product_sequence/i18n/es_AR.po
odoo/addons/product_sequence/i18n/es_CR.po
odoo/addons/product_sequence/i18n/es_EC.po
odoo/addons/product_sequence/i18n/es_MX.po
odoo/addons/product_sequence/i18n/es_VE.po
odoo/addons/product_sequence/i18n/et.po
odoo/addons/product_sequence/i18n/fi.po
odoo/addons/product_sequence/i18n/fr.po
odoo/addons/product_sequence/i18n/gl.po
odoo/addons/product_sequence/i18n/hr.po
odoo/addons/product_sequence/i18n/hu.po
odoo/addons/product_sequence/i18n/it.po
odoo/addons/product_sequence/i18n/ja.po
odoo/addons/product_sequence/i18n/lt.po
odoo/addons/product_sequence/i18n/mk.po
odoo/addons/product_sequence/i18n/mn.po
odoo/addons/product_sequence/i18n/nb.po
odoo/addons/product_sequence/i18n/nl.po
odoo/addons/product_sequence/i18n/pl.po
odoo/addons/product_sequence/i18n/product_sequence.pot
odoo/addons/product_sequence/i18n/pt.po
odoo/addons/product_sequence/i18n/pt_BR.po
odoo/addons/product_sequence/i18n/ro.po
odoo/addons/product_sequence/i18n/ru.po
odoo/addons/product_sequence/i18n/sl.po
odoo/addons/product_sequence/i18n/sr.po
odoo/addons/product_sequence/i18n/sv.po
odoo/addons/product_sequence/i18n/tr.po
odoo/addons/product_sequence/i18n/zh_CN.po
odoo/addons/product_sequence/models/__init__.py
odoo/addons/product_sequence/models/ir_sequence.py
odoo/addons/product_sequence/models/product_category.py
odoo/addons/product_sequence/models/product_product.py
odoo14_addon_product_sequence-14.0.2.0.1.dist-info/METADATA
odoo14_addon_product_sequence-14.0.2.0.1.dist-info/WHEEL
odoo14_addon_product_sequence-14.0.2.0.1.dist-info/top_level.txt
odoo14_addon_product_sequence-14.0.2.0.1.dist-info/RECORD
