Metadata-Version: 2.1
Name: odoo14-addon-product-sequence
Version: 14.0.2.0.1
Summary: Product Sequence
Home-page: https://github.com/OCA/product-attribute
Author: Zikzakmedia SL, Sodexis, Odoo Community Association (OCA)
Author-email: support@odoo-community.org
License: AGPL-3
Platform: UNKNOWN
Classifier: Programming Language :: Python
Classifier: Framework :: Odoo
Classifier: License :: OSI Approved :: GNU Affero General Public License v3
Requires-Python: >=3.6
Requires-Dist: odoo14-addon-product-code-unique
Requires-Dist: odoo (<14.1dev,>=14.0a)
